{"type":"Scene","props":{"width":375,"height":430},"compId":2,"child":[{"type":"Image","props":{"y":0,"x":0,"width":375,"skin":"resource/assets/img/wecat/failed_baseboard_1.png","sizeGrid":"15,15,100,15","left":0,"height":430},"compId":3,"child":[{"type":"Image","props":{"y":13,"width":347,"var":"image_icon","height":320,"centerX":0},"compId":4},{"type":"Label","props":{"y":359,"var":"lable_name","text":"游戏名字","fontSize":45,"color":"#ffffff","centerX":0,"bold":true},"compId":5}]}],"loadList":["resource/assets/img/wecat/failed_baseboard_1.png"],"loadList3D":[]}