{"type":"Scene","props":{"width":1080,"height":1920},"compId":2,"child":[{"type":"Image","props":{"top":0,"skin":"resource/assets/img/ui/moregame/mygame_baseboard_1.png","sizeGrid":"14,14,15,14","right":0,"left":0,"bottom":0},"compId":5},{"type":"Panel","props":{"var":"panel","top":280,"right":0,"left":0,"bottom":0},"compId":11},{"type":"Label","props":{"y":200,"x":415,"var":"tLabel","text":"我的小游戏","fontSize":50,"font":"Microsoft YaHei","centerX":0},"compId":8},{"type":"Image","props":{"x":10,"var":"image_back","top":200,"skin":"resource/assets/img/wecat/box_button_1.png"},"compId":12}],"loadList":["resource/assets/img/ui/moregame/mygame_baseboard_1.png","resource/assets/img/wecat/box_button_1.png"],"loadList3D":[]}